LICENSE
README.md
setup.py
opytimal/__init__.py
opytimal/_vars.py
opytimal/analytical.py
opytimal/arrays.py
opytimal/decorator.py
opytimal/dicts.py
opytimal/fenics.py
opytimal/files.py
opytimal/functions.py
opytimal/mathFunctions.py
opytimal/meshes.py
opytimal/modules.py
opytimal/numeric.py
opytimal/parallel.py
opytimal/plots.py
opytimal/profiler.py
opytimal/settings.py
opytimal/strings.py
opytimal/symbols.py
opytimal/tables.py
opytimal/tests.py
opytimal/types.py
opytimal.egg-info/PKG-INFO
opytimal.egg-info/SOURCES.txt
opytimal.egg-info/dependency_links.txt
opytimal.egg-info/requires.txt
opytimal.egg-info/top_level.txt
opytimal/demos/__init__.py
opytimal/demos/optHeat1D.py
opytimal/demos/optHeat2D.py
opytimal/demos/optPoisson1D.py
opytimal/demos/optPoisson2D.py
opytimal/demos/optPoisson3D.py
opytimal/demos/optStokes2D.py
opytimal/demos/optStokes3D.py